pypaddle
test
