Metadata-Version: 1.1
Name: pypaddle
Version: 0.3.2
Summary: Innvariant Group Sparse Neural Network Tools
Home-page: https://github.com/innvariant/pypaddle
Author: Chair of Data Science, University of Passau
Author-email: julian.stier@uni-passau.de
License: GPL3 License
Download-URL: https://github.com/innvariant/pypaddle/archive/0.3.2.tar.gz
Keywords: sparse,neural,networks,graph theory,pytorch
Platform: UNKNOWN
Classifier: Development Status :: 1 - Planning
Classifier: Environment :: Console
Classifier: Intended Audience :: Developers
Classifier: Intended Audience :: Science/Research
Classifier: License :: Other/Proprietary License
Classifier: Operating System :: POSIX :: Linux
Classifier: Programming Language :: Python
Classifier: Programming Language :: Python :: 3
Classifier: Programming Language :: Python :: 3.6
Classifier: Topic :: Scientific/Engineering
Classifier: Topic :: Scientific/Engineering :: Mathematics
Classifier: Topic :: Software Development :: Libraries
Classifier: Topic :: Software Development :: Libraries :: Python Modules
